Workbook

Sheet Leia-me
B2: refuturiza 360
B3: Sistema de Acompanhamento de Customer Success
B4: Emprego e Educação para Todos
B6: COMO USAR
B7: 1. Vá na aba CONTAS e preencha uma linha por cliente. Só edite as colunas AZUIS (entrada).
B8: 2. As colunas LARANJAS são calculadas automaticamente: uso de licenças, sub-scores, Health Score, Risco de Churn, Farol, Upgrade.
B9: 3. A aba PAINEL mostra os indicadores agregados (NRR, GRR, retenção de logos, ARR em risco, expansão potencial).
B10: 4. A aba METODOLOGIA explica cada cálculo, as premissas e os pontos cegos de CS.
B12: PARA ALIMENTAR O DASHBOARD
B13: Salve a aba CONTAS como CSV (Arquivo > Salvar como > CSV) e importe no dashboard HTML (botão "Importar CSV").
B15: VERDADE IMPORTANTE
B16: O Risco de Churn aqui é um PROXY baseado em sinais de CRM/relacionamento/suporte — não usa dados de uso do produto (logins, features).
... B19: As 12 linhas já preenchidas são EXEMPLOS fictícios. Substitua pelos seus clientes.

Sheet Contas
A1: CARTEIRA DE CLIENTES — preencha as colunas AZUIS
A2: Conta | B2: CSM | C2: Plano | D2: MRR inicial (12m atrás) | E2: MRR atual | F2: Licenças contratadas | G2: Licenças ativas | H2: Freq. login (0-100) | I2: Dias s/ contato | J2: Champion? | K2: Nº contatos engajados | L2: Tickets abertos | M2: Tickets críticos | N2: CSAT (0-100) | O2: NPS (-100..100) | P2: Pagamento | Q2: Estágio jornada | R2: Dias p/ renovação | S2: Uso licenças % | T2: Sub Adoção | U2: Sub Relac. | V2: Sub Suporte | W2: Sub Comercial | X2: Sub Sentim. | Y2: HEALTH SCORE | Z2: RISCO CHURN | AA2: FAROL | AB2: Upgrade? | AC2: Expansão pot. (R$/mês)
A3: Construtora Horizonte | B3: Marina | C3: Enterprise | D3: 32000 | E3: 38000 | F3: 500 | G3: 430 | H3: 82 | I3: 9 | J3: Sim | K3: 6 | L3: 2 | M3: 0 | N3: 88 | O3: 9 | P3: Em dia | Q3: Expansão | R3: 120 | S3: =IF($A3="","",IF(F3=0,0,G3/F3)) -> 0.86 | T3: =IF($A3="","",MEDIAN(0,0.6*(S3*100)+0.4*H3,100)) -> 84.4 | U3: =IF($A3="","",MEDIAN(0,IF(J3="Sim",45,0)+MEDIAN(0,K3*10,30)+MEDIAN(0,25-I3/3,25),100)) -> 97 | V3: =IF($A3="","",MEDIAN(0,0.5*N3+0.3*MEDIAN(0,100-L3*12,100)+0.2*MEDIAN(0,100-M3*40,100),100)) -> 86.8 | W3: =IF($A3="","",MEDIAN(0,IF(P3="Em dia",60,20)+IF(E3>=D3,40,IF(E3>=D3*0.85,20,0)),100)) -> 100 | X3: =IF($A3="","",MEDIAN(0,(O3+100)/2,100)) -> 54.5 | Y3: =IF($A3="","",ROUND(0.35*T3+0.2*U3+0.2*V3+0.15*W3+0.1*X3,0)) -> 87 | Z3: =IF($A3="","",ROUND(MEDIAN(0,(1-S3)*25+IF(H3<40,15,IF(H3<60,7,0))+IF(J3="Sim",0,18)+IF(K3<=1,10,0)+MEDIAN(0,I3/4,18)+M3*8+IF(E3<D3,12,0)+IF(P3="Atrasado",10,0)+IF(O3<0,8,0),100),0)) -> 6 | AA3: =IF(N3="","",IF(OR(E3=0,Y3<45,Z3>=65,AND(R3<=60,Y3<60,E3>0)),"Vermelho",IF(OR(AND(Y3>=45,Y3<70),AND(Z3>=45,Z3<65)),"Amarelo","Verde"))) -> Verde | AB3: =IF($A3="","",IF(AND(E3>0,OR(S3>=0.85,AND(Y3>=75,O3>=8,E3>=D3,S3>=0.7))),"Sim","Não")) -> Sim | AC3: =IF($A3="","",IF(AB3="Sim",ROUND(E3*0.25,0),0)) -> 9500
A4: Rede Bem Estar Saúde | B4: Rafael | C4: Growth | D4: 18000 | E4: 18000 | F4: 300 | G4: 96 | H4: 31 | I4: 54 | J4: Não | K4: 1 | L4: 5 | M4: 1 | N4: 61 | O4: 2 | P4: Em dia | Q4: Engajamento | R4: 160 | S4: =IF($A4="","",IF(F4=0,0,G4/F4)) -> 0.32 | T4: =IF($A4="","",MEDIAN(0,0.6*(S4*100)+0.4*H4,100)) -> 31.6 | U4: =IF($A4="","",MEDIAN(0,IF(J4="Sim",45,0)+MEDIAN(0,K4*10,30)+MEDIAN(0,25-I4/3,25),100)) -> 17 | V4: =IF($A4="","",MEDIAN(0,0.5*N4+0.3*MEDIAN(0,100-L4*12,100)+0.2*MEDIAN(0,100-M4*40,100),100)) -> 54.5 | W4: =IF($A4="","",MEDIAN(0,IF(P4="Em dia",60,20)+IF(E4>=D4,40,IF(E4>=D4*0.85,20,0)),100)) -> 100 | X4: =IF($A4="","",MEDIAN(0,(O4+100)/2,100)) -> 51 | Y4: =IF($A4="","",ROUND(0.35*T4+0.2*U4+0.2*V4+0.15*W4+0.1*X4,0)) -> 45 | Z4: =IF($A4="","",ROUND(MEDIAN(0,(1-S4)*25+IF(H4<40,15,IF(H4<60,7,0))+IF(J4="Sim",0,18)+IF(K4<=1,10,0)+MEDIAN(0,I4/4,18)+M4*8+IF(E4<D4,12,0)+IF(P4="Atrasado",10,0)+IF(O4<0,8,0),100),0)) -> 82 | AA4: =IF(N4="","",IF(OR(E4=0,Y4<45,Z4>=65,AND(R4<=60,Y4<60,E4>0)),"Vermelho",IF(OR(AND(Y4>=45,Y4<70),AND(Z4>=45,Z4<65)),"Amarelo","Verde"))) -> Vermelho | AB4: =IF($A4="","",IF(AND(E4>0,OR(S4>=0.85,AND(Y4>=75,O4>=8,E4>=D4,S4>=0.7))),"Sim","Não")) -> Não | AC4: =IF($A4="","",IF(AB4="Sim",ROUND(E4*0.25,0),0)) -> 0
A5: Grupo Varejo Sul | B5: Marina | C5: Enterprise | D5: 41000 | E5: 41000 | F5: 800 | G5: 740 | H5: 77 | I5: 14 | J5: Sim | K5: 8 | L5: 3 | M5: 0 | N5: 84 | O5: 8 | P5: Em dia | Q5: Renovação | R5: 35 | S5: =IF($A5="","",IF(F5=0,0,G5/F5)) -> 0.925 | T5: =IF($A5="","",MEDIAN(0,0.6*(S5*100)+0.4*H5,100)) -> 86.3 | U5: =IF($A5="","",MEDIAN(0,IF(J5="Sim",45,0)+MEDIAN(0,K5*10,30)+MEDIAN(0,25-I5/3,25),100)) -> 95.333333 | V5: =IF($A5="","",MEDIAN(0,0.5*N5+0.3*MEDIAN(0,100-L5*12,100)+0.2*MEDIAN(0,100-M5*40,100),100)) -> 81.2 | W5: =IF($A5="","",MEDIAN(0,IF(P5="Em dia",60,20)+IF(E5>=D5,40,IF(E5>=D5*0.85,20,0)),100)) -> 100 | X5: =IF($A5="","",MEDIAN(0,(O5+100)/2,100)) -> 54 | Y5: =IF($A5="","",ROUND(0.35*T5+0.2*U5+0.2*V5+0.15*W5+0.1*X5,0)) -> 86 | Z5: =IF($A5="","",ROUND(MEDIAN(0,(1-S5)*25+IF(H5<40,15,IF(H5<60,7,0))+IF(J5="Sim",0,18)+IF(K5<=1,10,0)+MEDIAN(0,I5/4,18)+M5*8+IF(E5<D5,12,0)+IF(P5="Atrasado",10,0)+IF(O5<0,8,0),100),0)) -> 5 | AA5: =IF(N5="","",IF(OR(E5=0,Y5<45,Z5>=65,AND(R5<=60,Y5<60,E5>0)),"Vermelho",IF(OR(AND(Y5>=45,Y5<70),AND(Z5>=45,Z5<65)),"Amarelo","Verde"))) -> Verde | AB5: =IF($A5="","",IF(AND(E5>0,OR(S5>=0.85,AND(Y5>=75,O5>=8,E5>=D5,S5>=0.7))),"Sim","Não")) -> Sim | AC5: =IF($A5="","",IF(AB5="Sim",ROUND(E5*0.25,0),0)) -> 10250
A6: TechNova Sistemas | B6: Bruno | C6: Growth | D6: 12000 | E6: 9000 | F6: 200 | G6: 70 | H6: 24 | I6: 71 | J6: Não | K6: 1 | L6: 7 | M6: 2 | N6: 48 | O6: -15 | P6: Atrasado | Q6: Renovação | R6: 35 | S6: =IF($A6="","",IF(F6=0,0,G6/F6)) -> 0.35 | T6: =IF($A6="","",MEDIAN(0,0.6*(S6*100)+0.4*H6,100)) -> 30.6 | U6: =IF($A6="","",MEDIAN(0,IF(J6="Sim",45,0)+MEDIAN(0,K6*10,30)+MEDIAN(0,25-I6/3,25),100)) -> 11.333333 | V6: =IF($A6="","",MEDIAN(0,0.5*N6+0.3*MEDIAN(0,100-L6*12,100)+0.2*MEDIAN(0,100-M6*40,100),100)) -> 32.8 | W6: =IF($A6="","",MEDIAN(0,IF(P6="Em dia",60,20)+IF(E6>=D6,40,IF(E6>=D6*0.85,20,0)),100)) -> 20 | X6: =IF($A6="","",MEDIAN(0,(O6+100)/2,100)) -> 42.5 | Y6: =IF($A6="","",ROUND(0.35*T6+0.2*U6+0.2*V6+0.15*W6+0.1*X6,0)) -> 27 | Z6: =IF($A6="","",ROUND(MEDIAN(0,(1-S6)*25+IF(H6<40,15,IF(H6<60,7,0))+IF(J6="Sim",0,18)+IF(K6<=1,10,0)+MEDIAN(0,I6/4,18)+M6*8+IF(E6<D6,12,0)+IF(P6="Atrasado",10,0)+IF(O6<0,8,0),100),0)) -> 100 | AA6: =IF(N6="","",IF(OR(E6=0,Y6<45,Z6>=65,AND(R6<=60,Y6<60,E6>0)),"Vermelho",IF(OR(AND(Y6>=45,Y6<70),AND(Z6>=45,Z6<65)),"Amarelo","Verde"))) -> Vermelho | AB6: =IF($A6="","",IF(AND(E6>0,OR(S6>=0.85,AND(Y6>=75,O6>=8,E6>=D6,S6>=0.7))),"Sim","Não")) -> Não | AC6: =IF($A6="","",IF(AB6="Sim",ROUND(E6*0.25,0),0)) -> 0
A7: Indústria Ferro Forte | B7: Rafael | C7: Starter | D7: 5000 | E7: 6500 | F7: 80 | G7: 74 | H7: 69 | I7: 18 | J7: Sim | K7: 4 | L7: 1 | M7: 0 | N7: 80 | O7: 7 | P7: Em dia | Q7: Adoção | R7: 240 | S7: =IF($A7="","",IF(F7=0,0,G7/F7)) -> 0.925 | T7: =IF($A7="","",MEDIAN(0,0.6*(S7*100)+0.4*H7,100)) -> 83.1 | U7: =IF($A7="","",MEDIAN(0,IF(J7="Sim",45,0)+MEDIAN(0,K7*10,30)+MEDIAN(0,25-I7/3,25),100)) -> 94 | V7: =IF($A7="","",MEDIAN(0,0.5*N7+0.3*MEDIAN(0,100-L7*12,100)+0.2*MEDIAN(0,100-M7*40,100),100)) -> 86.4 | W7: =IF($A7="","",MEDIAN(0,IF(P7="Em dia",60,20)+IF(E7>=D7,40,IF(E7>=D7*0.85,20,0)),100)) -> 100 | X7: =IF($A7="","",MEDIAN(0,(O7+100)/2,100)) -> 53.5 | Y7: =IF($A7="","",ROUND(0.35*T7+0.2*U7+0.2*V7+0.15*W7+0.1*X7,0)) -> 86 | Z7: =IF($A7="","",ROUND(MEDIAN(0,(1-S7)*25+IF(H7<40,15,IF(H7<60,7,0))+IF(J7="Sim",0,18)+IF(K7<=1,10,0)+MEDIAN(0,I7/4,18)+M7*8+IF(E7<D7,12,0)+IF(P7="Atrasado",10,0)+IF(O7<0,8,0),100),0)) -> 6 | AA7: =IF(N7="","",IF(OR(E7=0,Y7<45,Z7>=65,AND(R7<=60,Y7<60,E7>0)),"Vermelho",IF(OR(AND(Y7>=45,Y7<70),AND(Z7>=45,Z7<65)),"Amarelo","Verde"))) -> Verde | AB7: =IF($A7="","",IF(AND(E7>0,OR(S7>=0.85,AND(Y7>=75,O7>=8,E7>=D7,S7>=0.7))),"Sim","Não")) -> Sim | AC7: =IF($A7="","",IF(AB7="Sim",ROUND(E7*0.25,0),0)) -> 1625
A8: Logística Andorinha | B8: Bruno | C8: Growth | D8: 16000 | E8: 16000 | F8: 250 | G8: 235 | H8: 74 | I8: 22 | J8: Sim | K8: 5 | L8: 2 | M8: 0 | N8: 79 | O8: 6 | P8: Em dia | Q8: Expansão | R8: 120 | S8: =IF($A8="","",IF(F8=0,0,G8/F8)) -> 0.94 | T8: =IF($A8="","",MEDIAN(0,0.6*(S8*100)+0.4*H8,100)) -> 86 | U8: =IF($A8="","",MEDIAN(0,IF(J8="Sim",45,0)+MEDIAN(0,K8*10,30)+MEDIAN(0,25-I8/3,25),100)) -> 92.666667 | V8: =IF($A8="","",MEDIAN(0,0.5*N8+0.3*MEDIAN(0,100-L8*12,100)+0.2*MEDIAN(0,100-M8*40,100),100)) -> 82.3 | W8: =IF($A8="","",MEDIAN(0,IF(P8="Em dia",60,20)+IF(E8>=D8,40,IF(E8>=D8*0.85,20,0)),100)) -> 100 | X8: =IF($A8="","",MEDIAN(0,(O8+100)/2,100)) -> 53 | Y8: =IF($A8="","",ROUND(0.35*T8+0.2*U8+0.2*V8+0.15*W8+0.1*X8,0)) -> 85 | Z8: =IF($A8="","",ROUND(MEDIAN(0,(1-S8)*25+IF(H8<40,15,IF(H8<60,7,0))+IF(J8="Sim",0,18)+IF(K8<=1,10,0)+MEDIAN(0,I8/4,18)+M8*8+IF(E8<D8,12,0)+IF(P8="Atrasado",10,0)+IF(O8<0,8,0),100),0)) -> 7 | AA8: =IF(N8="","",IF(OR(E8=0,Y8<45,Z8>=65,AND(R8<=60,Y8<60,E8>0)),"Vermelho",IF(OR(AND(Y8>=45,Y8<70),AND(Z8>=45,Z8<65)),"Amarelo","Verde"))) -> Verde | AB8: =IF($A8="","",IF(AND(E8>0,OR(S8>=0.85,AND(Y8>=75,O8>=8,E8>=D8,S8>=0.7))),"Sim","Não")) -> Sim | AC8: =IF($A8="","",IF(AB8="Sim",ROUND(E8*0.25,0),0)) -> 4000
A9: Banco Coop Aliança | B9: Marina | C9: Enterprise | D9: 55000 | E9: 48000 | F9: 1000 | G9: 520 | H9: 41 | I9: 38 | J9: Não | K9: 2 | L9: 6 | M9: 1 | N9: 58 | O9: -5 | P9: Em dia | Q9: Renovação | R9: 35 | S9: =IF($A9="","",IF(F9=0,0,G9/F9)) -> 0.52 | T9: =IF($A9="","",MEDIAN(0,0.6*(S9*100)+0.4*H9,100)) -> 47.6 | U9: =IF($A9="","",MEDIAN(0,IF(J9="Sim",45,0)+MEDIAN(0,K9*10,30)+MEDIAN(0,25-I9/3,25),100)) -> 32.333333 | V9: =IF($A9="","",MEDIAN(0,0.5*N9+0.3*MEDIAN(0,100-L9*12,100)+0.2*MEDIAN(0,100-M9*40,100),100)) -> 49.4 | W9: =IF($A9="","",MEDIAN(0,IF(P9="Em dia",60,20)+IF(E9>=D9,40,IF(E9>=D9*0.85,20,0)),100)) -> 80 | X9: =IF($A9="","",MEDIAN(0,(O9+100)/2,100)) -> 47.5 | Y9: =IF($A9="","",ROUND(0.35*T9+0.2*U9+0.2*V9+0.15*W9+0.1*X9,0)) -> 50 | Z9: =IF($A9="","",ROUND(MEDIAN(0,(1-S9)*25+IF(H9<40,15,IF(H9<60,7,0))+IF(J9="Sim",0,18)+IF(K9<=1,10,0)+MEDIAN(0,I9/4,18)+M9*8+IF(E9<D9,12,0)+IF(P9="Atrasado",10,0)+IF(O9<0,8,0),100),0)) -> 75 | AA9: =IF(N9="","",IF(OR(E9=0,Y9<45,Z9>=65,AND(R9<=60,Y9<60,E9>0)),"Vermelho",IF(OR(AND(Y9>=45,Y9<70),AND(Z9>=45,Z9<65)),"Amarelo","Verde"))) -> Vermelho | AB9: =IF($A9="","",IF(AND(E9>0,OR(S9>=0.85,AND(Y9>=75,O9>=8,E9>=D9,S9>=0.7))),"Sim","Não")) -> Não | AC9: =IF($A9="","",IF(AB9="Sim",ROUND(E9*0.25,0),0)) -> 0
A10: Rede Educa Mais | B10: Rafael | C10: Growth | D10: 14000 | E10: 15500 | F10: 220 | G10: 198 | H10: 73 | I10: 11 | J10: Sim | K10: 5 | L10: 1 | M10: 0 | N10: 86 | O10: 9 | P10: Em dia | Q10: Advocacia | R10: 200 | S10: =IF($A10="","",IF(F10=0,0,G10/F10)) -> 0.9 | T10: =IF($A10="","",MEDIAN(0,0.6*(S10*100)+0.4*H10,100)) -> 83.2 | U10: =IF($A10="","",MEDIAN(0,IF(J10="Sim",45,0)+MEDIAN(0,K10*10,30)+MEDIAN(0,25-I10/3,25),100)) -> 96.333333 | V10: =IF($A10="","",MEDIAN(0,0.5*N10+0.3*MEDIAN(0,100-L10*12,100)+0.2*MEDIAN(0,100-M10*40,100),100)) -> 89.4 | W10: =IF($A10="","",MEDIAN(0,IF(P10="Em dia",60,20)+IF(E10>=D10,40,IF(E10>=D10*0.85,20,0)),100)) -> 100 | X10: =IF($A10="","",MEDIAN(0,(O10+100)/2,100)) -> 54.5 | Y10: =IF($A10="","",ROUND(0.35*T10+0.2*U10+0.2*V10+0.15*W10+0.1*X10,0)) -> 87 | Z10: =IF($A10="","",ROUND(MEDIAN(0,(1-S10)*25+IF(H10<40,15,IF(H10<60,7,0))+IF(J10="Sim",0,18)+IF(K10<=1,10,0)+MEDIAN(0,I10/4,18)+M10*8+IF(E10<D10,12,0)+IF(P10="Atrasado",10,0)+IF(O10<0,8,0),100),0)) -> 5 | AA10: =IF(N10="","",IF(OR(E10=0,Y10<45,Z10>=65,AND(R10<=60,Y10<60,E10>0)),"Vermelho",IF(OR(AND(Y10>=45,Y10<70),AND(Z10>=45,Z10<65)),"Amarelo","Verde"))) -> Verde | AB10: =IF($A10="","",IF(AND(E10>0,OR(S10>=0.85,AND(Y10>=75,O10>=8,E10>=D10,S10>=0.7))),"Sim","Não")) -> Sim | AC10: =IF($A10="","",IF(AB10="Sim",ROUND(E10*0.25,0),0)) -> 3875
A11: Atacado Real Distrib. | B11: Bruno | C11: Starter | D11: 4000 | E11: 4000 | F11: 60 | G11: 22 | H11: 28 | I11: 63 | J11: Não | K11: 1 | L11: 3 | M11: 0 | N11: 55 | O11: 0 | P11: Atrasado | Q11: Onboarding | R11: 300 | S11: =IF($A11="","",IF(F11=0,0,G11/F11)) -> 0.36666667 | T11: =IF($A11="","",MEDIAN(0,0.6*(S11*100)+0.4*H11,100)) -> 33.2 | U11: =IF($A11="","",MEDIAN(0,IF(J11="Sim",45,0)+MEDIAN(0,K11*10,30)+MEDIAN(0,25-I11/3,25),100)) -> 14 | V11: =IF($A11="","",MEDIAN(0,0.5*N11+0.3*MEDIAN(0,100-L11*12,100)+0.2*MEDIAN(0,100-M11*40,100),100)) -> 66.7 | W11: =IF($A11="","",MEDIAN(0,IF(P11="Em dia",60,20)+IF(E11>=D11,40,IF(E11>=D11*0.85,20,0)),100)) -> 60 | X11: =IF($A11="","",MEDIAN(0,(O11+100)/2,100)) -> 50 | Y11: =IF($A11="","",ROUND(0.35*T11+0.2*U11+0.2*V11+0.15*W11+0.1*X11,0)) -> 42 | Z11: =IF($A11="","",ROUND(MEDIAN(0,(1-S11)*25+IF(H11<40,15,IF(H11<60,7,0))+IF(J11="Sim",0,18)+IF(K11<=1,10,0)+MEDIAN(0,I11/4,18)+M11*8+IF(E11<D11,12,0)+IF(P11="Atrasado",10,0)+IF(O11<0,8,0),100),0)) -> 85 | AA11: =IF(N11="","",IF(OR(E11=0,Y11<45,Z11>=65,AND(R11<=60,Y11<60,E11>0)),"Vermelho",IF(OR(AND(Y11>=45,Y11<70),AND(Z11>=45,Z11<65)),"Amarelo","Verde"))) -> Vermelho | AB11: =IF($A11="","",IF(AND(E11>0,OR(S11>=0.85,AND(Y11>=75,O11>=8,E11>=D11,S11>=0.7))),"Sim","Não")) -> Não | AC11: =IF($A11="","",IF(AB11="Sim",ROUND(E11*0.25,0),0)) -> 0
A12: Hospital Vida Plena | B12: Marina | C12: Enterprise | D12: 38000 | E12: 44000 | F12: 700 | G12: 610 | H12: 80 | I12: 7 | J12: Sim | K12: 7 | L12: 2 | M12: 0 | N12: 90 | O12: 10 | P12: Em dia | Q12: Expansão | R12: 120 | S12: =IF($A12="","",IF(F12=0,0,G12/F12)) -> 0.87142857 | T12: =IF($A12="","",MEDIAN(0,0.6*(S12*100)+0.4*H12,100)) -> 84.285714 | U12: =IF($A12="","",MEDIAN(0,IF(J12="Sim",45,0)+MEDIAN(0,K12*10,30)+MEDIAN(0,25-I12/3,25),100)) -> 97.666667 | V12: =IF($A12="","",MEDIAN(0,0.5*N12+0.3*MEDIAN(0,100-L12*12,100)+0.2*MEDIAN(0,100-M12*40,100),100)) -> 87.8 | W12: =IF($A12="","",MEDIAN(0,IF(P12="Em dia",60,20)+IF(E12>=D12,40,IF(E12>=D12*0.85,20,0)),100)) -> 100 | X12: =IF($A12="","",MEDIAN(0,(O12+100)/2,100)) -> 55 | Y12: =IF($A12="","",ROUND(0.35*T12+0.2*U12+0.2*V12+0.15*W12+0.1*X12,0)) -> 87 | Z12: =IF($A12="","",ROUND(MEDIAN(0,(1-S12)*25+IF(H12<40,15,IF(H12<60,7,0))+IF(J12="Sim",0,18)+IF(K12<=1,10,0)+MEDIAN(0,I12/4,18)+M12*8+IF(E12<D12,12,0)+IF(P12="Atrasado",10,0)+IF(O12<0,8,0),100),0)) -> 5 | AA12: =IF(N12="","",IF(OR(E12=0,Y12<45,Z12>=65,AND(R12<=60,Y12<60,E12>0)),"Vermelho",IF(OR(AND(Y12>=45,Y12<70),AND(Z12>=45,Z12<65)),"Amarelo","Verde"))) -> Verde | AB12: =IF($A12="","",IF(AND(E12>0,OR(S12>=0.85,AND(Y12>=75,O12>=8,E12>=D12,S12>=0.7))),"Sim","Não")) -> Sim | AC12: =IF($A12="","",IF(AB12="Sim",ROUND(E12*0.25,0),0)) -> 11000
A13: Transportes Litoral | B13: Rafael | C13: Growth | D13: 13000 | E13: 13000 | F13: 180 | G13: 120 | H13: 52 | I13: 29 | J13: Sim | K13: 3 | L13: 4 | M13: 0 | N13: 70 | O13: 4 | P13: Em dia | Q13: Engajamento | R13: 160 | S13: =IF($A13="","",IF(F13=0,0,G13/F13)) -> 0.66666667 | T13: =IF($A13="","",MEDIAN(0,0.6*(S13*100)+0.4*H13,100)) -> 60.8 | U13: =IF($A13="","",MEDIAN(0,IF(J13="Sim",45,0)+MEDIAN(0,K13*10,30)+MEDIAN(0,25-I13/3,25),100)) -> 90.333333 | V13: =IF($A13="","",MEDIAN(0,0.5*N13+0.3*MEDIAN(0,100-L13*12,100)+0.2*MEDIAN(0,100-M13*40,100),100)) -> 70.6 | W13: =IF($A13="","",MEDIAN(0,IF(P13="Em dia",60,20)+IF(E13>=D13,40,IF(E13>=D13*0.85,20,0)),100)) -> 100 | X13: =IF($A13="","",MEDIAN(0,(O13+100)/2,100)) -> 52 | Y13: =IF($A13="","",ROUND(0.35*T13+0.2*U13+0.2*V13+0.15*W13+0.1*X13,0)) -> 74 | Z13: =IF($A13="","",ROUND(MEDIAN(0,(1-S13)*25+IF(H13<40,15,IF(H13<60,7,0))+IF(J13="Sim",0,18)+IF(K13<=1,10,0)+MEDIAN(0,I13/4,18)+M13*8+IF(E13<D13,12,0)+IF(P13="Atrasado",10,0)+IF(O13<0,8,0),100),0)) -> 23 | AA13: =IF(N13="","",IF(OR(E13=0,Y13<45,Z13>=65,AND(R13<=60,Y13<60,E13>0)),"Vermelho",IF(OR(AND(Y13>=45,Y13<70),AND(Z13>=45,Z13<65)),"Amarelo","Verde"))) -> Verde | AB13: =IF($A13="","",IF(AND(E13>0,OR(S13>=0.85,AND(Y13>=75,O13>=8,E13>=D13,S13>=0.7))),"Sim","Não")) -> Não | AC13: =IF($A13="","",IF(AB13="Sim",ROUND(E13*0.25,0),0)) -> 0
A14: AgroVerde Cooperativa | B14: Bruno | C14: Starter | D14: 6000 | E14: 7000 | F14: 90 | G14: 81 | H14: 66 | I14: 16 | J14: Sim | K14: 4 | L14: 0 | M14: 0 | N14: 82 | O14: 8 | P14: Em dia | Q14: Adoção | R14: 240 | S14: =IF($A14="","",IF(F14=0,0,G14/F14)) -> 0.9 | T14: =IF($A14="","",MEDIAN(0,0.6*(S14*100)+0.4*H14,100)) -> 80.4 | U14: =IF($A14="","",MEDIAN(0,IF(J14="Sim",45,0)+MEDIAN(0,K14*10,30)+MEDIAN(0,25-I14/3,25),100)) -> 94.666667 | V14: =IF($A14="","",MEDIAN(0,0.5*N14+0.3*MEDIAN(0,100-L14*12,100)+0.2*MEDIAN(0,100-M14*40,100),100)) -> 91 | W14: =IF($A14="","",MEDIAN(0,IF(P14="Em dia",60,20)+IF(E14>=D14,40,IF(E14>=D14*0.85,20,0)),100)) -> 100 | X14: =IF($A14="","",MEDIAN(0,(O14+100)/2,100)) -> 54 | Y14: =IF($A14="","",ROUND(0.35*T14+0.2*U14+0.2*V14+0.15*W14+0.1*X14,0)) -> 86 | Z14: =IF($A14="","",ROUND(MEDIAN(0,(1-S14)*25+IF(H14<40,15,IF(H14<60,7,0))+IF(J14="Sim",0,18)+IF(K14<=1,10,0)+MEDIAN(0,I14/4,18)+M14*8+IF(E14<D14,12,0)+IF(P14="Atrasado",10,0)+IF(O14<0,8,0),100),0)) -> 7 | AA14: =IF(N14="","",IF(OR(E14=0,Y14<45,Z14>=65,AND(R14<=60,Y14<60,E14>0)),"Vermelho",IF(OR(AND(Y14>=45,Y14<70),AND(Z14>=45,Z14<65)),"Amarelo","Verde"))) -> Verde | AB14: =IF($A14="","",IF(AND(E14>0,OR(S14>=0.85,AND(Y14>=75,O14>=8,E14>=D14,S14>=0.7))),"Sim","Não")) -> Sim | AC14: =IF($A14="","",IF(AB14="Sim",ROUND(E14*0.25,0),0)) -> 1750
S15: =IF($A15="","",IF(F15=0,0,G15/F15)) | T15: =IF($A15="","",MEDIAN(0,0.6*(S15*100)+0.4*H15,100)) | U15: =IF($A15="","",MEDIAN(0,IF(J15="Sim",45,0)+MEDIAN(0,K15*10,30)+MEDIAN(0,25-I15/3,25),100)) | V15: =IF($A15="","",MEDIAN(0,0.5*N15+0.3*MEDIAN(0,100-L15*12,100)+0.2*MEDIAN(0,100-M15*40,100),100)) | W15: =IF($A15="","",MEDIAN(0,IF(P15="Em dia",60,20)+IF(E15>=D15,40,IF(E15>=D15*0.85,20,0)),100)) | X15: =IF($A15="","",MEDIAN(0,(O15+100)/2,100)) | Y15: =IF($A15="","",ROUND(0.35*T15+0.2*U15+0.2*V15+0.15*W15+0.1*X15,0)) | Z15: =IF($A15="","",ROUND(MEDIAN(0,(1-S15)*25+IF(H15<40,15,IF(H15<60,7,0))+IF(J15="Sim",0,18)+IF(K15<=1,10,0)+MEDIAN(0,I15/4,18)+M15*8+IF(E15<D15,12,0)+IF(P15="Atrasado",10,0)+IF(O15<0,8,0),100),0)) | AA15: =IF(N15="","",IF(OR(E15=0,Y15<45,Z15>=65,AND(R15<=60,Y15<60,E15>0)),"Vermelho",IF(OR(AND(Y15>=45,Y15<70),AND(Z15>=45,Z15<65)),"Amarelo","Verde"))) | AB15: =IF($A15="","",IF(AND(E15>0,OR(S15>=0.85,AND(Y15>=75,O15>=8,E15>=D15,S15>=0.7))),"Sim","Não")) | AC15: =IF($A15="","",IF(AB15="Sim",ROUND(E15*0.25,0),0))
S16: =IF($A16="","",IF(F16=0,0,G16/F16)) | T16: =IF($A16="","",MEDIAN(0,0.6*(S16*100)+0.4*H16,100)) | U16: =IF($A16="","",MEDIAN(0,IF(J16="Sim",45,0)+MEDIAN(0,K16*10,30)+MEDIAN(0,25-I16/3,25),100)) | V16: =IF($A16="","",MEDIAN(0,0.5*N16+0.3*MEDIAN(0,100-L16*12,100)+0.2*MEDIAN(0,100-M16*40,100),100)) | W16: =IF($A16="","",MEDIAN(0,IF(P16="Em dia",60,20)+IF(E16>=D16,40,IF(E16>=D16*0.85,20,0)),100)) | X16: =IF($A16="","",MEDIAN(0,(O16+100)/2,100)) | Y16: =IF($A16="","",ROUND(0.35*T16+0.2*U16+0.2*V16+0.15*W16+0.1*X16,0)) | Z16: =IF($A16="","",ROUND(MEDIAN(0,(1-S16)*25+IF(H16<40,15,IF(H16<60,7,0))+IF(J16="Sim",0,18)+IF(K16<=1,10,0)+MEDIAN(0,I16/4,18)+M16*8+IF(E16<D16,12,0)+IF(P16="Atrasado",10,0)+IF(O16<0,8,0),100),0)) | AA16: =IF(N16="","",IF(OR(E16=0,Y16<45,Z16>=65,AND(R16<=60,Y16<60,E16>0)),"Vermelho",IF(OR(AND(Y16>=45,Y16<70),AND(Z16>=45,Z16<65)),"Amarelo","Verde"))) | AB16: =IF($A16="","",IF(AND(E16>0,OR(S16>=0.85,AND(Y16>=75,O16>=8,E16>=D16,S16>=0.7))),"Sim","Não")) | AC16: =IF($A16="","",IF(AB16="Sim",ROUND(E16*0.25,0),0))
S17: =IF($A17="","",IF(F17=0,0,G17/F17)) | T17: =IF($A17="","",MEDIAN(0,0.6*(S17*100)+0.4*H17,100)) | U17: =IF($A17="","",MEDIAN(0,IF(J17="Sim",45,0)+MEDIAN(0,K17*10,30)+MEDIAN(0,25-I17/3,25),100)) | V17: =IF($A17="","",MEDIAN(0,0.5*N17+0.3*MEDIAN(0,100-L17*12,100)+0.2*MEDIAN(0,100-M17*40,100),100)) | W17: =IF($A17="","",MEDIAN(0,IF(P17="Em dia",60,20)+IF(E17>=D17,40,IF(E17>=D17*0.85,20,0)),100)) | X17: =IF($A17="","",MEDIAN(0,(O17+100)/2,100)) | Y17: =IF($A17="","",ROUND(0.35*T17+0.2*U17+0.2*V17+0.15*W17+0.1*X17,0)) | Z17: =IF($A17="","",ROUND(MEDIAN(0,(1-S17)*25+IF(H17<40,15,IF(H17<60,7,0))+IF(J17="Sim",0,18)+IF(K17<=1,10,0)+MEDIAN(0,I17/4,18)+M17*8+IF(E17<D17,12,0)+IF(P17="Atrasado",10,0)+IF(O17<0,8,0),100),0)) | AA17: =IF(N17="","",IF(OR(E17=0,Y17<45,Z17>=65,AND(R17<=60,Y17<60,E17>0)),"Vermelho",IF(OR(AND(Y17>=45,Y17<70),AND(Z17>=45,Z17<65)),"Amarelo","Verde"))) | AB17: =IF($A17="","",IF(AND(E17>0,OR(S17>=0.85,AND(Y17>=75,O17>=8,E17>=D17,S17>=0.7))),"Sim","Não")) | AC17: =IF($A17="","",IF(AB17="Sim",ROUND(E17*0.25,0),0))
S18: =IF($A18="","",IF(F18=0,0,G18/F18)) | T18: =IF($A18="","",MEDIAN(0,0.6*(S18*100)+0.4*H18,100)) | U18: =IF($A18="","",MEDIAN(0,IF(J18="Sim",45,0)+MEDIAN(0,K18*10,30)+MEDIAN(0,25-I18/3,25),100)) | V18: =IF($A18="","",MEDIAN(0,0.5*N18+0.3*MEDIAN(0,100-L18*12,100)+0.2*MEDIAN(0,100-M18*40,100),100)) | W18: =IF($A18="","",MEDIAN(0,IF(P18="Em dia",60,20)+IF(E18>=D18,40,IF(E18>=D18*0.85,20,0)),100)) | X18: =IF($A18="","",MEDIAN(0,(O18+100)/2,100)) | Y18: =IF($A18="","",ROUND(0.35*T18+0.2*U18+0.2*V18+0.15*W18+0.1*X18,0)) | Z18: =IF($A18="","",ROUND(MEDIAN(0,(1-S18)*25+IF(H18<40,15,IF(H18<60,7,0))+IF(J18="Sim",0,18)+IF(K18<=1,10,0)+MEDIAN(0,I18/4,18)+M18*8+IF(E18<D18,12,0)+IF(P18="Atrasado",10,0)+IF(O18<0,8,0),100),0)) | AA18: =IF(N18="","",IF(OR(E18=0,Y18<45,Z18>=65,AND(R18<=60,Y18<60,E18>0)),"Vermelho",IF(OR(AND(Y18>=45,Y18<70),AND(Z18>=45,Z18<65)),"Amarelo","Verde"))) | AB18: =IF($A18="","",IF(AND(E18>0,OR(S18>=0.85,AND(Y18>=75,O18>=8,E18>=D18,S18>=0.7))),"Sim","Não")) | AC18: =IF($A18="","",IF(AB18="Sim",ROUND(E18*0.25,0),0))
S19: =IF($A19="","",IF(F19=0,0,G19/F19)) | T19: =IF($A19="","",MEDIAN(0,0.6*(S19*100)+0.4*H19,100)) | U19: =IF($A19="","",MEDIAN(0,IF(J19="Sim",45,0)+MEDIAN(0,K19*10,30)+MEDIAN(0,25-I19/3,25),100)) | V19: =IF($A19="","",MEDIAN(0,0.5*N19+0.3*MEDIAN(0,100-L19*12,100)+0.2*MEDIAN(0,100-M19*40,100),100)) | W19: =IF($A19="","",MEDIAN(0,IF(P19="Em dia",60,20)+IF(E19>=D19,40,IF(E19>=D19*0.85,20,0)),100)) | X19: =IF($A19="","",MEDIAN(0,(O19+100)/2,100)) | Y19: =IF($A19="","",ROUND(0.35*T19+0.2*U19+0.2*V19+0.15*W19+0.1*X19,0)) | Z19: =IF($A19="","",ROUND(MEDIAN(0,(1-S19)*25+IF(H19<40,15,IF(H19<60,7,0))+IF(J19="Sim",0,18)+IF(K19<=1,10,0)+MEDIAN(0,I19/4,18)+M19*8+IF(E19<D19,12,0)+IF(P19="Atrasado",10,0)+IF(O19<0,8,0),100),0)) | AA19: =IF(N19="","",IF(OR(E19=0,Y19<45,Z19>=65,AND(R19<=60,Y19<60,E19>0)),"Vermelho",IF(OR(AND(Y19>=45,Y19<70),AND(Z19>=45,Z19<65)),"Amarelo","Verde"))) | AB19: =IF($A19="","",IF(AND(E19>0,OR(S19>=0.85,AND(Y19>=75,O19>=8,E19>=D19,S19>=0.7))),"Sim","Não")) | AC19: =IF($A19="","",IF(AB19="Sim",ROUND(E19*0.25,0),0))
S20: =IF($A20="","",IF(F20=0,0,G20/F20)) | T20: =IF($A20="","",MEDIAN(0,0.6*(S20*100)+0.4*H20,100)) | U20: =IF($A20="","",MEDIAN(0,IF(J20="Sim",45,0)+MEDIAN(0,K20*10,30)+MEDIAN(0,25-I20/3,25),100)) | V20: =IF($A20="","",MEDIAN(0,0.5*N20+0.3*MEDIAN(0,100-L20*12,100)+0.2*MEDIAN(0,100-M20*40,100),100)) | W20: =IF($A20="","",MEDIAN(0,IF(P20="Em dia",60,20)+IF(E20>=D20,40,IF(E20>=D20*0.85,20,0)),100)) | X20: =IF($A20="","",MEDIAN(0,(O20+100)/2,100)) | Y20: =IF($A20="","",ROUND(0.35*T20+0.2*U20+0.2*V20+0.15*W20+0.1*X20,0)) | Z20: =IF($A20="","",ROUND(MEDIAN(0,(1-S20)*25+IF(H20<40,15,IF(H20<60,7,0))+IF(J20="Sim",0,18)+IF(K20<=1,10,0)+MEDIAN(0,I20/4,18)+M20*8+IF(E20<D20,12,0)+IF(P20="Atrasado",10,0)+IF(O20<0,8,0),100),0)) | AA20: =IF(N20="","",IF(OR(E20=0,Y20<45,Z20>=65,AND(R20<=60,Y20<60,E20>0)),"Vermelho",IF(OR(AND(Y20>=45,Y20<70),AND(Z20>=45,Z20<65)),"Amarelo","Verde"))) | AB20: =IF($A20="","",IF(AND(E20>0,OR(S20>=0.85,AND(Y20>=75,O20>=8,E20>=D20,S20>=0.7))),"Sim","Não")) | AC20: =IF($A20="","",IF(AB20="Sim",ROUND(E20*0.25,0),0))
S21: =IF($A21="","",IF(F21=0,0,G21/F21)) | T21: =IF($A21="","",MEDIAN(0,0.6*(S21*100)+0.4*H21,100)) | U21: =IF($A21="","",MEDIAN(0,IF(J21="Sim",45,0)+MEDIAN(0,K21*10,30)+MEDIAN(0,25-I21/3,25),100)) | V21: =IF($A21="","",MEDIAN(0,0.5*N21+0.3*MEDIAN(0,100-L21*12,100)+0.2*MEDIAN(0,100-M21*40,100),100)) | W21: =IF($A21="","",MEDIAN(0,IF(P21="Em dia",60,20)+IF(E21>=D21,40,IF(E21>=D21*0.85,20,0)),100)) | X21: =IF($A21="","",MEDIAN(0,(O21+100)/2,100)) | Y21: =IF($A21="","",ROUND(0.35*T21+0.2*U21+0.2*V21+0.15*W21+0.1*X21,0)) | Z21: =IF($A21="","",ROUND(MEDIAN(0,(1-S21)*25+IF(H21<40,15,IF(H21<60,7,0))+IF(J21="Sim",0,18)+IF(K21<=1,10,0)+MEDIAN(0,I21/4,18)+M21*8+IF(E21<D21,12,0)+IF(P21="Atrasado",10,0)+IF(O21<0,8,0),100),0)) | AA21: =IF(N21="","",IF(OR(E21=0,Y21<45,Z21>=65,AND(R21<=60,Y21<60,E21>0)),"Vermelho",IF(OR(AND(Y21>=45,Y21<70),AND(Z21>=45,Z21<65)),"Amarelo","Verde"))) | AB21: =IF($A21="","",IF(AND(E21>0,OR(S21>=0.85,AND(Y21>=75,O21>=8,E21>=D21,S21>=0.7))),"Sim","Não")) | AC21: =IF($A21="","",IF(AB21="Sim",ROUND(E21*0.25,0),0))
S22: =IF($A22="","",IF(F22=0,0,G22/F22)) | T22: =IF($A22="","",MEDIAN(0,0.6*(S22*100)+0.4*H22,100)) | U22: =IF($A22="","",MEDIAN(0,IF(J22="Sim",45,0)+MEDIAN(0,K22*10,30)+MEDIAN(0,25-I22/3,25),100)) | V22: =IF($A22="","",MEDIAN(0,0.5*N22+0.3*MEDIAN(0,100-L22*12,100)+0.2*MEDIAN(0,100-M22*40,100),100)) | W22: =IF($A22="","",MEDIAN(0,IF(P22="Em dia",60,20)+IF(E22>=D22,40,IF(E22>=D22*0.85,20,0)),100)) | X22: =IF($A22="","",MEDIAN(0,(O22+100)/2,100)) | Y22: =IF($A22="","",ROUND(0.35*T22+0.2*U22+0.2*V22+0.15*W22+0.1*X22,0)) | Z22: =IF($A22="","",ROUND(MEDIAN(0,(1-S22)*25+IF(H22<40,15,IF(H22<60,7,0))+IF(J22="Sim",0,18)+IF(K22<=1,10,0)+MEDIAN(0,I22/4,18)+M22*8+IF(E22<D22,12,0)+IF(P22="Atrasado",10,0)+IF(O22<0,8,0),100),0)) | AA22: =IF(N22="","",IF(OR(E22=0,Y22<45,Z22>=65,AND(R22<=60,Y22<60,E22>0)),"Vermelho",IF(OR(AND(Y22>=45,Y22<70),AND(Z22>=45,Z22<65)),"Amarelo","Verde"))) | AB22: =IF($A22="","",IF(AND(E22>0,OR(S22>=0.85,AND(Y22>=75,O22>=8,E22>=D22,S22>=0.7))),"Sim","Não")) | AC22: =IF($A22="","",IF(AB22="Sim",ROUND(E22*0.25,0),0))
S23: =IF($A23="","",IF(F23=0,0,G23/F23)) | T23: =IF($A23="","",MEDIAN(0,0.6*(S23*100)+0.4*H23,100)) | U23: =IF($A23="","",MEDIAN(0,IF(J23="Sim",45,0)+MEDIAN(0,K23*10,30)+MEDIAN(0,25-I23/3,25),100)) | V23: =IF($A23="","",MEDIAN(0,0.5*N23+0.3*MEDIAN(0,100-L23*12,100)+0.2*MEDIAN(0,100-M23*40,100),100)) | W23: =IF($A23="","",MEDIAN(0,IF(P23="Em dia",60,20)+IF(E23>=D23,40,IF(E23>=D23*0.85,20,0)),100)) | X23: =IF($A23="","",MEDIAN(0,(O23+100)/2,100)) | Y23: =IF($A23="","",ROUND(0.35*T23+0.2*U23+0.2*V23+0.15*W23+0.1*X23,0)) | Z23: =IF($A23="","",ROUND(MEDIAN(0,(1-S23)*25+IF(H23<40,15,IF(H23<60,7,0))+IF(J23="Sim",0,18)+IF(K23<=1,10,0)+MEDIAN(0,I23/4,18)+M23*8+IF(E23<D23,12,0)+IF(P23="Atrasado",10,0)+IF(O23<0,8,0),100),0)) | AA23: =IF(N23="","",IF(OR(E23=0,Y23<45,Z23>=65,AND(R23<=60,Y23<60,E23>0)),"Vermelho",IF(OR(AND(Y23>=45,Y23<70),AND(Z23>=45,Z23<65)),"Amarelo","Verde"))) | AB23: =IF($A23="","",IF(AND(E23>0,OR(S23>=0.85,AND(Y23>=75,O23>=8,E23>=D23,S23>=0.7))),"Sim","Não")) | AC23: =IF($A23="","",IF(AB23="Sim",ROUND(E23*0.25,0),0))
S24: =IF($A24="","",IF(F24=0,0,G24/F24)) | T24: =IF($A24="","",MEDIAN(0,0.6*(S24*100)+0.4*H24,100)) | U24: =IF($A24="","",MEDIAN(0,IF(J24="Sim",45,0)+MEDIAN(0,K24*10,30)+MEDIAN(0,25-I24/3,25),100)) | V24: =IF($A24="","",MEDIAN(0,0.5*N24+0.3*MEDIAN(0,100-L24*12,100)+0.2*MEDIAN(0,100-M24*40,100),100)) | W24: =IF($A24="","",MEDIAN(0,IF(P24="Em dia",60,20)+IF(E24>=D24,40,IF(E24>=D24*0.85,20,0)),100)) | X24: =IF($A24="","",MEDIAN(0,(O24+100)/2,100)) | Y24: =IF($A24="","",ROUND(0.35*T24+0.2*U24+0.2*V24+0.15*W24+0.1*X24,0)) | Z24: =IF($A24="","",ROUND(MEDIAN(0,(1-S24)*25+IF(H24<40,15,IF(H24<60,7,0))+IF(J24="Sim",0,18)+IF(K24<=1,10,0)+MEDIAN(0,I24/4,18)+M24*8+IF(E24<D24,12,0)+IF(P24="Atrasado",10,0)+IF(O24<0,8,0),100),0)) | AA24: =IF(N24="","",IF(OR(E24=0,Y24<45,Z24>=65,AND(R24<=60,Y24<60,E24>0)),"Vermelho",IF(OR(AND(Y24>=45,Y24<70),AND(Z24>=45,Z24<65)),"Amarelo","Verde"))) | AB24: =IF($A24="","",IF(AND(E24>0,OR(S24>=0.85,AND(Y24>=75,O24>=8,E24>=D24,S24>=0.7))),"Sim","Não")) | AC24: =IF($A24="","",IF(AB24="Sim",ROUND(E24*0.25,0),0))
S25: =IF($A25="","",IF(F25=0,0,G25/F25)) | T25: =IF($A25="","",MEDIAN(0,0.6*(S25*100)+0.4*H25,100)) | U25: =IF($A25="","",MEDIAN(0,IF(J25="Sim",45,0)+MEDIAN(0,K25*10,30)+MEDIAN(0,25-I25/3,25),100)) | V25: =IF($A25="","",MEDIAN(0,0.5*N25+0.3*MEDIAN(0,100-L25*12,100)+0.2*MEDIAN(0,100-M25*40,100),100)) | W25: =IF($A25="","",MEDIAN(0,IF(P25="Em dia",60,20)+IF(E25>=D25,40,IF(E25>=D25*0.85,20,0)),100)) | X25: =IF($A25="","",MEDIAN(0,(O25+100)/2,100)) | Y25: =IF($A25="","",ROUND(0.35*T25+0.2*U25+0.2*V25+0.15*W25+0.1*X25,0)) | Z25: =IF($A25="","",ROUND(MEDIAN(0,(1-S25)*25+IF(H25<40,15,IF(H25<60,7,0))+IF(J25="Sim",0,18)+IF(K25<=1,10,0)+MEDIAN(0,I25/4,18)+M25*8+IF(E25<D25,12,0)+IF(P25="Atrasado",10,0)+IF(O25<0,8,0),100),0)) | AA25: =IF(N25="","",IF(OR(E25=0,Y25<45,Z25>=65,AND(R25<=60,Y25<60,E25>0)),"Vermelho",IF(OR(AND(Y25>=45,Y25<70),AND(Z25>=45,Z25<65)),"Amarelo","Verde"))) | AB25: =IF($A25="","",IF(AND(E25>0,OR(S25>=0.85,AND(Y25>=75,O25>=8,E25>=D25,S25>=0.7))),"Sim","Não")) | AC25: =IF($A25="","",IF(AB25="Sim",ROUND(E25*0.25,0),0))
S26: =IF($A26="","",IF(F26=0,0,G26/F26)) | T26: =IF($A26="","",MEDIAN(0,0.6*(S26*100)+0.4*H26,100)) | U26: =IF($A26="","",MEDIAN(0,IF(J26="Sim",45,0)+MEDIAN(0,K26*10,30)+MEDIAN(0,25-I26/3,25),100)) | V26: =IF($A26="","",MEDIAN(0,0.5*N26+0.3*MEDIAN(0,100-L26*12,100)+0.2*MEDIAN(0,100-M26*40,100),100)) | W26: =IF($A26="","",MEDIAN(0,IF(P26="Em dia",60,20)+IF(E26>=D26,40,IF(E26>=D26*0.85,20,0)),100)) | X26: =IF($A26="","",MEDIAN(0,(O26+100)/2,100)) | Y26: =IF($A26="","",ROUND(0.35*T26+0.2*U26+0.2*V26+0.15*W26+0.1*X26,0)) | Z26: =IF($A26="","",ROUND(MEDIAN(0,(1-S26)*25+IF(H26<40,15,IF(H26<60,7,0))+IF(J26="Sim",0,18)+IF(K26<=1,10,0)+MEDIAN(0,I26/4,18)+M26*8+IF(E26<D26,12,0)+IF(P26="Atrasado",10,0)+IF(O26<0,8,0),100),0)) | AA26: =IF(N26="","",IF(OR(E26=0,Y26<45,Z26>=65,AND(R26<=60,Y26<60,E26>0)),"Vermelho",IF(OR(AND(Y26>=45,Y26<70),AND(Z26>=45,Z26<65)),"Amarelo","Verde"))) | AB26: =IF($A26="","",IF(AND(E26>0,OR(S26>=0.85,AND(Y26>=75,O26>=8,E26>=D26,S26>=0.7))),"Sim","Não")) | AC26: =IF($A26="","",IF(AB26="Sim",ROUND(E26*0.25,0),0))
... S122: =IF($A122="","",IF(F122=0,0,G122/F122)) | T122: =IF($A122="","",MEDIAN(0,0.6*(S122*100)+0.4*H122,100)) | U122: =IF($A122="","",MEDIAN(0,IF(J122="Sim",45,0)+MEDIAN(0,K122*10,30)+MEDIAN(0,25-I122/3,25),100)) | V122: =IF($A122="","",MEDIAN(0,0.5*N122+0.3*MEDIAN(0,100-L122*12,100)+0.2*MEDIAN(0,100-M122*40,100),100)) | W122: =IF($A122="","",MEDIAN(0,IF(P122="Em dia",60,20)+IF(E122>=D122,40,IF(E122>=D122*0.85,20,0)),100)) | X122: =IF($A122="","",MEDIAN(0,(O122+100)/2,100)) | Y122: =IF($A122="","",ROUND(0.35*T122+0.2*U122+0.2*V122+0.15*W122+0.1*X122,0)) | Z122: =IF($A122="","",ROUND(MEDIAN(0,(1-S122)*25+IF(H122<40,15,IF(H122<60,7,0))+IF(J122="Sim",0,18)+IF(K122<=1,10,0)+MEDIAN(0,I122/4,18)+M122*8+IF(E122<D122,12,0)+IF(P122="Atrasado",10,0)+IF(O122<0,8,0),100),0)) | AA122: =IF(N122="","",IF(OR(E122=0,Y122<45,Z122>=65,AND(R122<=60,Y122<60,E122>0)),"Vermelho",IF(OR(AND(Y122>=45,Y122<70),AND(Z122>=45,Z122<65)),"Amarelo","Verde"))) | AB122: =IF($A122="","",IF(AND(E122>0,OR(S122>=0.85,AND(Y122>=75,O122>=8,E122>=D122,S122>=0.7))),"Sim","Não")) | AC122: =IF($A122="","",IF(AB122="Sim",ROUND(E122*0.25,0),0))

Sheet Painel
B2: PAINEL DE CUSTOMER SUCCESS
B3: Indicadores agregados — recalculados a partir da aba Contas
B5: NRR — Net Revenue Retention | C5: =IF(SUM(Contas!D3:D122)=0,0,SUM(Contas!E3:E122)/SUM(Contas!D3:D122)) -> 1.023622 | E5: Métrica nº 1 do B2B SaaS. >100% = base cresce mesmo perdendo clientes.
B6: GRR — Gross Revenue Retention | C6: =IF(SUM(Contas!D3:D122)=0,0,SUMPRODUCT((Contas!E3:E122<Contas!D3:D122)*Contas!E3:E122+(Contas!E3:E122>=Contas!D3:D122)*Contas!D3:D122)/SUM(Contas!D3:D122)) -> 0.96062992 | E6: Retenção sem crédito de expansão. Mede vazamento puro.
B7: Retenção de logos | C7: =IF(COUNTIF(Contas!D3:D122,">0")=0,0,COUNTIFS(Contas!E3:E122,">0",Contas!D3:D122,">0")/COUNTIF(Contas!D3:D122,">0")) -> 1 | E7: % de contas que continuaram (não churnaram).
B8: ARR ativo total | C8: =SUMIF(Contas!E3:E122,">0")*12 -> 3120000 | E8: Receita recorrente anual das contas ativas.
B9: Expansion MRR | C9: =SUMPRODUCT((Contas!E3:E122>0)*((Contas!E3:E122-Contas!D3:D122)>0)*(Contas!E3:E122-Contas!D3:D122)) -> 16000 | E9: Soma dos aumentos de MRR nas contas retidas.
B10: ARR em risco (farol vermelho) | C10: =SUMIFS(Contas!E3:E122,Contas!AA3:AA122,"Vermelho",Contas!E3:E122,">0")*12 -> 948000 | E10: Receita anual exposta em contas de risco.
B11: Health Score médio (ativos) | C11: =IFERROR(AVERAGEIFS(Contas!Y3:Y122,Contas!E3:E122,">0"),0) -> 70.166667 | E11: Saúde média da carteira ativa (0-100).
B12: Contas saudáveis (verde) | C12: =COUNTIFS(Contas!AA3:AA122,"Verde",Contas!E3:E122,">0") -> 8
B13: Contas em atenção (amarelo) | C13: =COUNTIFS(Contas!AA3:AA122,"Amarelo",Contas!E3:E122,">0") -> 0
B14: Contas em risco (vermelho) | C14: =COUNTIFS(Contas!AA3:AA122,"Vermelho",Contas!E3:E122,">0") -> 4
B15: Oportunidades de upgrade | C15: =COUNTIF(Contas!AB3:AB122,"Sim") -> 7 | E15: Contas prontas para expansão/upsell.
B16: Expansão potencial (anual) | C16: =SUM(Contas!AC3:AC122)*12 -> 504000 | E16: Receita anual adicional estimada se concretizar upgrades.

Sheet Metodologia
B2: Metodologia, premissas e pontos cegos
B4: HEALTH SCORE (0-100) — média ponderada de 5 dimensões:
B5: • Adoção/uso (35%): uso de licenças (ativas/contratadas) + frequência de login
B6: • Relacionamento (20%): champion, nº de contatos engajados (multithreading), dias sem contato
B7: • Suporte (20%): tickets abertos, tickets críticos, CSAT
B8: • Comercial (15%): status de pagamento, tendência de MRR
B9: • Sentimento (10%): NPS
B10: Os pesos são ponto de partida de mercado — recalibre contra seu churn real.
B12: FAROL DE RISCO (a regra mais severa vence):
B13: • Vermelho: health < 45 OU churn >= 65 OU (renovação <= 60 dias E health < 60)
B14: • Amarelo: health 45-69 OU churn 45-64
B15: • Verde: health >= 70 E churn < 45
... B33: LIMITAÇÃO PRINCIPAL: sem dados de uso do produto, o churn é um PROXY de CRM — útil, mas não preditivo validado.
